hodopy/__init__.py
hodopy/hodopy.py
hodopy-0.0.1.1.dist-info/METADATA
hodopy-0.0.1.1.dist-info/WHEEL
hodopy-0.0.1.1.dist-info/entry_points.txt
hodopy-0.0.1.1.dist-info/license_files/LICENSE
hodopy-0.0.1.1.dist-info/RECORD
