Metadata-Version: 2.1
Name: hodopy
Version: 0.0.1.1
Summary: A package for Hodograph Control Curves
Project-URL: Bug Tracker, https://github.com/shkwonmtl/hodopy/issues
Project-URL: Homepage, https://github.com/shkwonmtl/hodopy
Author-email: Hwan Pyo Moon <hpmoon@dongguk.edu>, Soo Hyun Kim <5hkim@skku.edu>, Song-Hwa Kwon <skwon@catholic.ac.kr>
License: MIT License
Classifier: License :: OSI Approved :: MIT License
Classifier: Operating System :: OS Independent
Classifier: Programming Language :: Python :: 3
Requires-Python: >=3.6
Requires-Dist: numpy>=1.19.4
